[
  {
    "authorizations": [
      {
        "principalId": "9a74af6f-d153-4348-988a-e2672920bee9",
        "roleDefinitionId": "8e3af657-a8ff-443c-a75c-2fe8c4bcb635"
      }
    ],
    "createdBy": {
      "applicationId": "04b07795-8ddb-461a-bbee-02f9e1bf7b46",
      "oid": "b98555c5-cdf7-47df-9c9e-04a0776f47e3",
      "puid": "10033FFF801BEEC0"
    },
    "createdDateTime": "2021-06-14T12:16:22.217580+00:00",
    "id": "/subscriptions/0a52391c-0d81-434e-90b4-d04f5c670e8a/resourceGroups/rg-DataBricks-dev/providers/Microsoft.Databricks/workspaces/dbw-Dev-DataBricksExplore",
    "location": "northeurope",
    "managedResourceGroupId": "/subscriptions/0a52391c-0d81-434e-90b4-d04f5c670e8a/resourceGroups/rg-databricks-dbw-Dev-DataBricksExplore-pfsgkskeky3pc",
    "name": "dbw-Dev-DataBricksExplore",
    "parameters": {
      "customPrivateSubnetName": {
        "type": "String",
        "value": "snet-DBricksPrivate"
      },
      "customPublicSubnetName": {
        "type": "String",
        "value": "snet-DBricksPublic"
      },
      "customVirtualNetworkId": {
        "type": "String",
        "value": "/subscriptions/0a52391c-0d81-434e-90b4-d04f5c670e8a/resourceGroups/rg-DataBricks-dev/providers/Microsoft.Network/virtualNetworks/vnet-Dev-DataBricksExplore"
      },
      "enableFedRampCertification": {
        "type": "Bool",
        "value": false
      },
      "enableNoPublicIp": {
        "type": "Bool",
        "value": false
      },
      "encryption": null,
      "natGatewayName": {
        "type": "String",
        "value": "nat-gateway"
      },
      "prepareEncryption": {
        "type": "Bool",
        "value": false
      },
      "publicIpName": {
        "type": "String",
        "value": "nat-gw-public-ip"
      },
      "relayNamespaceName": {
        "type": "String",
        "value": "dbrelaymz5elgkpw7whq"
      },
      "requireInfrastructureEncryption": {
        "type": "Bool",
        "value": false
      },
      "resourceTags": {
        "type": "Object",
        "value": {
          "Environment": "Dev",
          "Project": "DataBricksExplore",
          "application": "databricks",
          "databricks-environment": "true"
        }
      },
      "storageAccountName": {
        "type": "String",
        "value": "dbstoragemz5elgkpw7whq"
      },
      "storageAccountSkuName": {
        "type": "String",
        "value": "Standard_GRS"
      },
      "vnetAddressPrefix": {
        "type": "String",
        "value": "10.139"
      }
    },
    "provisioningState": "Succeeded",
    "resourceGroup": "rg-DataBricks-dev",
    "sku": {
      "name": "premium",
      "tier": null
    },
    "storageAccountIdentity": null,
    "tags": {
      "Environment": "Dev",
      "Project": "DataBricksExplore"
    },
    "type": "Microsoft.Databricks/workspaces",
    "uiDefinitionUri": null,
    "updatedBy": {
      "applicationId": "04b07795-8ddb-461a-bbee-02f9e1bf7b46",
      "oid": "b98555c5-cdf7-47df-9c9e-04a0776f47e3",
      "puid": "10033FFF801BEEC0"
    },
    "workspaceId": "5952758580137745",
    "workspaceUrl": "adb-5952758580137745.5.azuredatabricks.net"
  }
]
